Etl/Execute.py
Etl/Extrator.py
Etl/Helper.py
Etl/Loader.py
Etl/Treatment_extras.py
Etl/Treatment_tracking.py
Etl/Treatment_tracking_pme.py
Etl/__init__.py
etl_csm_pet-0.0.6.dist-info/LICENSE
etl_csm_pet-0.0.6.dist-info/METADATA
etl_csm_pet-0.0.6.dist-info/WHEEL
etl_csm_pet-0.0.6.dist-info/top_level.txt
etl_csm_pet-0.0.6.dist-info/RECORD
