Metadata-Version: 2.1
Name: etl-csm-pet
Version: 0.0.6
Summary: Pacote de ETL
Home-page: https://gitdev.clarobrasil.mobi/vendas-claro/csm/etl
Author: ingloriamori
Author-email: francisco.froes@globalhitss.com.br
License: MIT
Keywords: python,etl
Classifier: License :: OSI Approved :: MIT License
Classifier: Programming Language :: Python :: 3.9
Classifier: Operating System :: OS Independent
Requires-Python: >=3.9
License-File: LICENSE
Requires-Dist: numpy
Requires-Dist: pandas
Requires-Dist: orjson
Requires-Dist: SQLAlchemy
Requires-Dist: psycopg2-binary
Provides-Extra: dev
Requires-Dist: twine (>=4.0.2) ; extra == 'dev'
